fix_plugin_gcp/__init__.py
fix_plugin_gcp/collector.py
fix_plugin_gcp/config.py
fix_plugin_gcp/gcp_client.py
fix_plugin_gcp/utils.py
fix_plugin_gcp/resources/__init__.py
fix_plugin_gcp/resources/aiplatform.py
fix_plugin_gcp/resources/base.py
fix_plugin_gcp/resources/billing.py
fix_plugin_gcp/resources/cloudfunctions.py
fix_plugin_gcp/resources/compute.py
fix_plugin_gcp/resources/container.py
fix_plugin_gcp/resources/filestore.py
fix_plugin_gcp/resources/firestore.py
fix_plugin_gcp/resources/monitoring.py
fix_plugin_gcp/resources/pubsub.py
fix_plugin_gcp/resources/scc.py
fix_plugin_gcp/resources/sqladmin.py
fix_plugin_gcp/resources/storage.py
test/__init__.py
test/aiplatform_test.py
test/conftest.py
test/firestore_test.py
test/random_client.py
test/test_base.py
test/test_billing.py
test/test_cloudfunctions.py
test/test_collector.py
test/test_compute.py
test/test_config.py
test/test_container.py
test/test_filestore.py
test/test_monitoring.py
test/test_scc.py
test/test_sqladmin.py
test/test_storage.py
fixinventory_plugin_gcp-4.2.0.dist-info/METADATA
fixinventory_plugin_gcp-4.2.0.dist-info/WHEEL
fixinventory_plugin_gcp-4.2.0.dist-info/entry_points.txt
fixinventory_plugin_gcp-4.2.0.dist-info/top_level.txt
fixinventory_plugin_gcp-4.2.0.dist-info/RECORD
